Metadata-Version: 2.1
Name: odoo12-addon-mrp-stock-orderpoint-manual-procurement
Version: 12.0.1.0.1
Summary: Updates the value of MO Responsible and keeps trackof changes regarding this field
Home-page: https://github.com/OCA/manufacture
Author: Eficent, Odoo Community Association (OCA)
Author-email: support@odoo-community.org
License: AGPL-3
Platform: UNKNOWN
Classifier: Programming Language :: Python
Classifier: Framework :: Odoo
Classifier: Framework :: Odoo :: 12.0
Classifier: License :: OSI Approved :: GNU Affero General Public License v3
Requires-Python: >=3.5
Requires-Dist: odoo12-addon-stock-orderpoint-manual-procurement
Requires-Dist: odoo (<12.1dev,>=12.0a)
